LICENSE
MANIFEST.in
README.rst
obspyh5.py
setup.py
test_obspyh5.py
obspyh5.egg-info/PKG-INFO
obspyh5.egg-info/SOURCES.txt
obspyh5.egg-info/dependency_links.txt
obspyh5.egg-info/entry_points.txt
obspyh5.egg-info/not-zip-safe
obspyh5.egg-info/pbr.json
obspyh5.egg-info/requires.txt
obspyh5.egg-info/top_level.txt