Metadata-Version: 1.0
Name: obspyh5
Version: 0.2.2
Summary: hdf5 write/read support for obspy
Home-page: https://github.com/trichter/obspyh5
Author: Tom Eulenfeld
Author-email: tom.eulenfeld@gmail.com
License: MIT
Platform: UNKNOWN
